dataframe_helpers/__init__.py
dataframe_helpers/calculate_efficiency.py
dataframe_helpers/chunk_data.py
dataframe_helpers/dataframe_helpers.py
dataframe_helpers/flattened_apply.py
dataframe_helpers/generic.py
dataframe_helpers/group_apply.py
dataframe_helpers/markdownMaker.py
dataframe_helpers/merge.py
dataframe_helpers/pickleIO.py
dataframe_helpers-0.0.10.dist-info/licenses/LICENCE
dataframe_helpers-0.0.10.dist-info/METADATA
dataframe_helpers-0.0.10.dist-info/WHEEL
dataframe_helpers-0.0.10.dist-info/top_level.txt
dataframe_helpers-0.0.10.dist-info/RECORD
