Metadata-Version: 2.4
Name: dataframe_helpers
Version: 0.0.10
Summary: some helpers for pandas dataframes
Home-page: https://github.com/RPeschke/dataframe_helpers
Author: Richard Peschke
Author-email: peschke@hawaii.edu
Project-URL: Bug Tracker, https://github.com/RPeschke/dataframe_helpers/issues
Classifier: Programming Language :: Python :: 3
Classifier: License :: OSI Approved :: MIT License
Classifier: Operating System :: OS Independent
Requires-Python: >=3.6
License-File: LICENCE
Requires-Dist: pandas
Dynamic: author
Dynamic: author-email
Dynamic: classifier
Dynamic: description
Dynamic: description-content-type
Dynamic: home-page
Dynamic: license-file
Dynamic: project-url
Dynamic: requires-dist
Dynamic: requires-python
Dynamic: summary
